{
  "slug": "how-to-work-with-psychedelic-insights-about-belonging-and-community",
  "title": "How to Work with Psychedelic Insights About Belonging and Community",
  "categorySlug": "the-integration",
  "categoryName": "The Integration",
  "dateISO": "2026-04-29T17:02:05.706Z",
  "body": "<h2>How to Work with Psychedelic Insights About Belonging and Community</h2>\n\n<h3>1. Opening hook - The Quiet Moment When I Felt Everything Connect</h3>\n\n<p>There was a night, under a veiled sky, sitting alone on a mossy rock in the woods after a modest mushroom dose, that I suddenly felt it - that deep, wild thread of belonging that wove me into the dark soil, the whispering trees, the ancient stars. It wasn’t just a feeling. It was a knowing, a sudden, unshakable certainty that I was part of something vast, ancient, alive. That sense of “I am home” stretched out beyond my skin, beyond my mind, beyond the small self that usually defines me.</p>\n\n<p>I’ve never forgotten that moment. It changed how I see myself, how I move through the world. This wasn’t some fleeting trip high or a flashy hallucination; it was a glimpse into a connectedness that we all crave but so often feel maddeningly distant from. If you’ve ever felt that pull - like you’re missing a thread in the fabric of community, like you’re an island in a sea of faces - you’re not alone.</p>\n\n<p>Psychedelics have a curious way of stripping down the usual jangling noise in our heads, inviting something deeper to emerge. Belonging and community come up often in sessions and journal entries. But those moments of cosmic belonging don’t always land smoothly in the chaos of daily life. How do you take a feeling that vast and make it real when you’re back in the office, or sitting at the dinner table, or scrolling endlessly through your phone? How do you work with these insights without losing them, or worse, making them into something you’re afraid to talk about?</p>\n\n<p>That’s what I want to explore here. Over years of working with psychedelic therapy, reading the researchers, and yes, those late-night sessions with mushrooms, I’ve seen how belonging can become both a revelation and a challenge. It’s a thread that calls us out of isolation, but it also asks us to face parts of ourselves and our communities that may feel broken or out of reach.</p>\n\n<p>If you’re curious about what belonging really means on a psychedelic journey and how you can fold those insights back into your life, grab a cup of tea and come walk with me through the terrain of connection - from the neurons firing in your brain to the human relationships that make us feel alive. And if you want to read a beautifully clear deep dive on how psychedelics change the mind, I always recommend <a href=\"https://www.amazon.com/dp/1594774021?tag=spankyspinola-20\" target=\"_blank\" rel=\"nofollow sponsored\">How to Change Your Mind by Michael Pollan</a>. It’s a warm, grounded guide to what these medicines can reveal.</p>\n\n<h3>2. What Belonging Means in the Brain - The Science Behind the Feeling</h3>\n\n<p>Belonging isn’t just a poetic idea; it has tangible roots in the brain’s wiring. When we talk about feeling connected, we’re often referring to a network of neural systems that regulate social bonds, safety, and emotional tuning. The brain’s default mode network (DMN), in particular, is a key player. This network is often active when the mind is at rest, engaged in self-referential thinking - ruminating about the self, your place in the world, your relationships.</p>\n\n<p>One of the hallmark effects of psychedelics is their ability to quiet down the DMN’s chatter. Researchers like Robin Carhart-Harris have shown that under psilocybin, the brain’s usual patterns loosen up. This disintegration of the DMN is linked to ego dissolution - the sense that the boundary between self and other softens or disappears. That’s the doorway to the deep, often ineffable feeling of belonging. When the brain’s rigid sense of “I” lets go, we experience ourselves as part of a larger whole.</p>\n\n<p>But there’s more. Neurochemically, psychedelics boost serotonin activity, especially on the 5-HT2A receptor, which seems to play a role in social cognition. This shift can encourage empathy, openness, and a breakdown of social barriers. It’s why people often report feeling more compassionate and connected after a ceremony or session. The brain’s salience network, which directs attention to what matters, also changes, making social stimuli feel more vivid and meaningful.</p>\n\n<p>This isn’t just brain mumbo jumbo. The way your neurons fire relates directly to how you experience community and belonging. Scientists like Matthew Johnson and Bill Richards have pointed out that these effects open a “critical window” where old social fears and rigid thought patterns can soften, making room for new connections.</p>\n\n<p>Understanding this biological basis helps make sense of why belonging feels so urgent and sometimes fragile during psychedelic trips. It’s a moment when your brain is rewired, temporarily less defensive, more open to connection. But it also means that the insights you get are tied deeply to your brain chemistry - so how you come down from that state matters a lot for keeping those feelings alive.</p>\n\n<h3>3. The Science and Stories Behind Psychedelic Belonging</h3>\n\n<p>There’s a growing body of research that threads together psychedelic experiences and social bonding. For example, a 2017 study by Griffiths and colleagues on psilocybin-assisted therapy for anxiety and depression showed participants reporting increased feelings of connection to others and more meaningful social relationships months after their sessions. Those weren’t just happy vibes - they corresponded to measurable changes in personality traits, especially openness and agreeableness.</p>\n\n<p>Another interesting study in 2021 by Pokorny and Preller examined how psychedelics like LSD affect social cognition. They found enhancements in empathy, emotional understanding, and decreased social anxiety. These findings suggest psychedelics can literally recalibrate how we see and feel about other people.</p>\n\n<p>Looking back, the work of Stanislav Grof, one of the pioneers of psychedelic therapy, emphasized the importance of connectedness to community and the cosmos as a core healing factor. His sessions often revealed that trauma and disconnection aren’t just psychological but deeply spiritual ruptures. Reclaiming a sense of belonging on these journeys can be a key part of healing wounds left by isolation.</p>\n\n<p>Paul Stamets, the mycologist who has done so much to popularize mushroom medicine, often talks about fungi as a metaphor for networks - underground threads binding ecosystems, far beyond individual organisms. This idea that our personal sense of belonging mirrors natural systems is a beautiful lens to hold when working with psychedelic insights.</p>\n\n<p>If you want to track your own experiences with belonging after a session, keeping a journal helps immensely. I swear by a simple <a href=\"https://www.amazon.com/dp/B09VK9S4JB?tag=spankyspinola-20\" target=\"_blank\" rel=\"nofollow sponsored\">leather-bound notebook</a>. Writing down the moments of connection - not just during the trip but in the days that follow - can reveal patterns and deepen the shifts you’re making.</p>\n\n<h3>4. How to Work Practical Psychedelic Insights Into Your Sense of Community</h3>\n\n<p>Having experienced the cosmic sense of belonging, I’ve learned the importance of bringing those feelings into real, everyday connections. It’s easy to get caught in the “trip bubble” and then feel isolated afterward, as if the experience was some gift that slipped through your fingers. But you can plant the seeds of psychedelic insights in your daily life with intention and care.</p>\n\n<p>Start small. Maybe it’s reaching out to a friend you haven’t talked to in a while, or joining a local group where you feel seen. Psychedelic medicine often reminds us that our connection to others is part of healing, so honoring that by showing up authentically matters. I remember after a deep psilocybin ceremony, I challenged myself to have weekly dinners with people who support me, no distractions, just presence.</p>\n\n<p>Volunteering or participating in community rituals can also help ground belonging outside the self. I’ve found that working with nature-based groups or attending circle gatherings offers a container where the psychedelic insight into interconnectedness can thrive. You’re not alone in these feelings - there are spaces where they are shared and understood.</p>\n\n<p>There’s also power in expressing those insights creatively - whether through art, music, or writing. I often recommend journaling as a daily practice, especially after a session. Writing down your thoughts about community, connection, and your place in the world cements those feelings. If you’re looking for a journal, check out this <a href=\"https://www.amazon.com/dp/B09VK9S4JB?tag=spankyspinola-20\" target=\"_blank\" rel=\"nofollow sponsored\">Journaling Notebook Leather Bound</a>, which has been a solid companion on many of my journeys.</p>\n\n<p>Don’t forget to take care of your body, too. Trauma and disconnection often live in the body - in tension, in pain. Bessel van der Kolk’s book <a href=\"https://www.amazon.com/dp/0525510311?tag=spankyspinola-20\" target=\"_blank\" rel=\"nofollow sponsored\">The Body Keeps the Score</a> is a treasure trove for understanding how physical healing connects to emotional and social belonging. Bodywork, mindful movement, or simple breathwork alongside psychedelic therapy can help you embody your insights fully.</p>\n\n<h3>5. The Roadblocks: Common Challenges in Maintaining Psychedelic Belonging</h3>\n\n<p>Even with the best intentions, holding onto feelings of belonging after a psychedelic experience is tricky. One of the biggest challenges I see is the return of old isolation patterns - those mental voices that whisper, “You don’t belong here,” or “People won’t understand you.” Psychedelic states often reveal these narratives starkly, but they don’t always disappear when the trip fades.</p>\n\n<p>There’s also the risk of romanticizing the experience. Sometimes people expect that deep sense of connection to be permanent or come rushing back on demand. This can lead to disappointment and disillusionment. Integration takes patience. It’s a gradual weaving of insights into your daily lived reality, not a single moment of transformation that solves all loneliness overnight.</p>\n\n<p>Another barrier is social stigma. When we talk about belonging through the lens of psychedelics, we’re often stepping outside mainstream norms. Feeling misunderstood or judged can shut down vulnerability, which is essential for connection. I encourage folks to seek out trusted peers or support groups where they can share their experiences without fear.</p>\n\n<p>On a practical note, sometimes the community you’re in feels fractured or unsupportive. Psychedelic medicine can open your eyes to toxic dynamics or patterns of disconnection in families or friend groups. That recognition is painful but necessary. Setting boundaries or seeking new social circles can be part of working through these challenges.</p>\n\n<p>One of the best ways I’ve found to move through these difficulties is holding a kind, curious stance toward yourself. Recognize that belonging is a process, not a destination. Journaling can help here - if you’re feeling stuck, writing out your fears, hopes, and questions can make the invisible visible. I keep coming back to the suggestion to carry a journal like this <a href=\"https://www.amazon.com/dp/B09VK9S4JB?tag=spankyspinola-20\" target=\"_blank\" rel=\"nofollow sponsored\">leather-bound one</a> so when those moments hit, you have a place to land your thoughts.</p>\n\n<h3>6. Integration as a Lifelong Practice - Making Belonging Part of Your Daily Life</h3>\n\n<p>I’ve found that working with psychedelic insights on belonging is less about a single event and more a lifelong practice. The way you bring the medicine into your daily interactions shapes how those feelings grow or fade. Integration isn’t a one-time checklist but an unfolding relationship with yourself and others.</p>\n\n<p>Regular rituals help. These might be as simple as morning gratitude reflections on people you appreciate, or attending weekly community meetings that remind you of shared values. Being intentional about connection means showing up consistently, even when it’s messy or uncomfortable. It is often in those imperfect moments that belonging becomes real.</p>\n\n<p>Another integration tip is mindfulness - learning to notice when you’re closing off, when old fears about rejection rise up. Breath awareness or body scans can anchor you back into the present moment, where you don’t have to buy into negative self-talk. This practice creates space for authentic connection.</p>\n\n<p>Don’t underestimate the role of service. Giving your time and energy to others can build meaningful bonds and remind you that you matter. Psychedelic experiences often reveal how interconnected we are; living that truth might mean volunteering, mentoring, or simply listening deeply to a friend.</p>\n\n<p>Also, remember to revisit your psychedelic insights regularly. Continue reading or listening to voices in this field to keep the inspiration alive. Books like <a href=\"https://www.amazon.com/dp/1594774021?tag=spankyspinola-20\" target=\"_blank\" rel=\"nofollow sponsored\">How to Change Your Mind</a> by Michael Pollan can bring fresh perspective when you feel your connection waning.</p>\n\n<p>Finally, integration benefits from self-compassion. The path to belonging is never linear. There are ups and downs, moments of connection and times of loneliness. Give yourself permission to move at your own pace, holding the insights gently as you build your community.</p>\n\n<h3>7. Closing Reflection - Belonging as a Living Question</h3>\n\n<p>Here’s something I’ve come to understand - belonging is not a final answer. It’s more like a living question we carry through our days and nights. Psychedelic experiences can fling that question open, sometimes in dazzling clarity, other times in messy fragments. The invitation is to walk with that uncertainty, not rush to close it off.</p>\n\n<p>What if belonging means leaning into our shared vulnerability - those moments when we admit we don’t have all the answers, when we reach out despite fear? What if it’s less about finding a perfect community and more about practicing presence with those around us, however imperfect they or we may be?</p>\n\n<p>There’s a kind of humility in psychedelic belonging, a reminder that we are small parts of a vast whole, yet those small parts matter deeply. It can be tempting to hold tightly to moments of connection like precious trophies, but I’ve learned that true belonging asks for letting go - of control, of certainty, even of the self. This is why the work continues long after the trip ends.</p>\n\n<p>Maybe what you take away most is not a tidy feeling but an invitation: to be awake to the connections you already have, to seek new ones in unexpected places, to carry your belonging like a soft ember in your chest. When you do, you discover that you are never truly alone.</p>\n\n<p>These insights have shaped my life in ways I’m still unpacking. If they speak to you, I encourage patience and kindness with yourself. Keep reading, keep reflecting, and when you’re ready, keep reaching out. Our belonging is waiting.</p>",
  "excerpt": "How to Work with Psychedelic Insights About Belonging and Community \n\n You just came back from a trip, feeling like you touched something bigger than yourself. Maybe it was a moment of pure connectio...",
  "heroImage": "https://quiet-medicine.b-cdn.net/library/lib-26.webp",
  "ogImage": "https://quiet-medicine.b-cdn.net/library/lib-27.webp",
  "heroAlt": "Illustration for How to Work with Psychedelic Insights About Belonging and Community",
  "readingTime": 5,
  "status": "queued",
  "queued_at": "2026-04-29T17:02:05.706Z",
  "published_at": "2026-03-20T08:00:00.000Z",
  "publishDate": "2026-03-20",
  "wordCount": 2301
}