{
  "slug": "role-intention-microdosing",
  "title": "The Role of Intention in Microdosing",
  "categorySlug": "the-microdose",
  "categoryName": "The Microdose",
  "dateISO": "2025-05-21T07:46:00.000Z",
  "body": "<h2>The Role of Intention in Microdosing</h2>\n\n<h3>1. Opening hook: A story about intention and the subtle shift</h3>\n\n<p>When I first started microdosing, it felt like I was tuning a radio dial, trying to find a clearer frequency in the static of daily life. I didn’t approach it blindly; I had heard from early pioneers like James Fadiman that intention was the secret ingredient to making these small doses meaningful. Still, it took me a few rounds of trial and error before I truly grasped how profoundly intention shapes the microdosing experience.</p>\n\n<p>One memorable morning stands out. I measured my dose carefully on my <a href=\"https://www.amazon.com/dp/B078SZX3ML?tag=spankyspinola-20\" target=\"_blank\" rel=\"nofollow sponsored\">Milligram Scale 0.001g Precision</a> because even a fraction off can tilt the experience. I reminded myself why I was doing this: to bring a little more creativity and mental clarity into my work without losing grip on reality. Without much fanfare, I went about my day. Hours later, I noticed a subtle shift in my mindset - a lightness of thought, a gentle curiosity toward problems that usually felt rigid and fixed. Yet, I wasn’t floating off into fantasy or tripping out. It was as if a small door had opened inside my mind, inviting fresh ideas to flow in.</p>\n\n<p>Contrast that with another time, when I microdosed but didn’t set any intention. I was distracted, a bit anxious, not really present. That day, the effects were muted or maybe just muddled. Nothing clicked. It dawned on me that the chemicals were only half the story. The other half was my mental state, my focus, my attitude. Without conscious intention, the subtle magic of microdosing can easily slip past unnoticed or get lost in the noise of everyday life.</p>\n\n<p>This simple reality - intention shapes experience - is not new. In fact, it echoes ancient practices from indigenous shamans to modern psychonauts. But it raises a fascinating question: What is it about intention that interacts with microdosing to create meaningful change? Why does it matter so much, even when the doses are so tiny? And how can we use that understanding to get the most out of this emerging practice?</p>\n\n<p>In this article, I want to take you beyond the buzzwords and hype, digging into the science, the research, and the practical wisdom behind intention in microdosing. We’ll explore how setting your mental compass before dosing can transform subtle shifts into lasting growth, and how you can make intention a real, living part of your mushroom medicine journey.</p>\n\n<h3>2. Understanding intention: The invisible catalyst</h3>\n\n<p>Intention is often described as a mental or emotional state that directs your focus toward a goal. But with microdosing, it's much more than just a goal or a vague wish. Intention acts as an invisible catalyst that shapes how the brain responds to even the smallest amounts of psychedelic compounds.</p>\n\n<p>Neuroscientifically, intention seems to work by priming certain neural pathways and networks before the compounds exert their effects. When you set an intention, you’re activating brain areas involved in attention, motivation, and emotional regulation - primarily the prefrontal cortex and the anterior cingulate cortex. These regions help filter what information gets priority, deciding what we focus on and what we let fade into the background.</p>\n\n<p>Microdosing involves sub-perceptual doses of psilocybin, typically between 0.1 to 0.3 grams of dried mushrooms. At these levels, the drug doesn’t cause overt hallucinations or a break from reality but subtly tweaks brain function. Research suggests microdosing influences the serotonin 2A receptors, enhancing connectivity across brain networks, especially the default mode network (DMN), which is often overactive in depression and rumination.</p>\n\n<p>But here’s where intention becomes fascinating. When you enter this altered neural state with a clear purpose, the brain’s plasticity - the capacity to reorganize itself - increases selectively around circuits that align with your intention. It’s like the brain’s volume knob is turned up, but which channels get amplified depends on what you’re mentally tuned into.</p>\n\n<p>Think of it like a flashlight in a dark room. The microdose brightens the whole room a bit, but your intention moves the beam, spotlighting parts of the room that might otherwise stay hidden. Without intention, the light may just wash over everything dimly. With intention, it illuminates what matters most to you.</p>\n\n<p>I’ve seen this echoed in the writings of researchers like Robin Carhart-Harris, whose studies show psilocybin-assisted therapy works best when patients have clear therapeutic goals. While his work mainly focuses on higher doses, the principle extends to microdosing: The mindset and expectations you bring dramatically shape the outcome.</p>\n\n<p>Setting intention turns microdosing from a random chemical interaction into a directed experience. It’s not just about the biology of the mushroom, but about how your mind chooses to engage with the subtle shifts it creates. This understanding opens the door to conscious, active participation rather than passive consumption.</p>\n\n<h3>3. What the research says: Studies on intention and microdosing</h3>\n\n<p>Scientific inquiry into microdosing is still in its infancy compared to full-dose psychedelic therapy, but some studies have begun to hint at the role of intention in the outcomes observed.</p>\n\n<p>One notable investigation came from Dr. Thomas Anderson and his team at Imperial College London in 2019. They conducted a randomized, placebo-controlled microdosing study, and one interesting aspect was the emphasis on participants’ expectations and mindset. They found that those who approached microdosing with curiosity and intention reported more positive effects on creativity and mood compared to those who treated it as a mere experiment or distraction. Though the sample size was small, it highlighted how mindset operates as a filter that shapes the experience.</p>\n\n<p>Another key study led by Vince Polito and Richard Stevenson at Macquarie University in 2019 surveyed over 1,200 microdosers. The research documented that people who set specific intentions - such as improving focus, reducing anxiety, or enhancing creativity - tended to experience more consistent benefits. Polito’s work emphasized the psychological structure surrounding microdosing as crucial, rather than the pharmacology alone.</p>\n\n<p>Looking beyond microdosing, the broader psychedelic research field - particularly studies on full-dose psilocybin - offers insights. Roland Griffiths’ work at Johns Hopkins University shows that intention-setting and preparation significantly predict the quality and therapeutic impact of psychedelic sessions. Participants who engaged in pre-session reflection and intention-setting reported more meaningful insights and enduring changes.</p>\n\n<p>Similarly, Stanislav Grof, a pioneer in psychedelic research, has long pointed out the importance of \"set and setting.\" While \"set\" often refers to mindset, intention is a refined concept within that frame; it involves consciously choosing what you want to invite or explore in the experience. Grof’s observations, although mostly with higher doses of psychedelics, set a foundation that we can translate to microdosing.</p>\n\n<p>Michael Pollan, in his excellent book <a href=\"https://www.amazon.com/dp/1594774021?tag=spankyspinola-20\" target=\"_blank\" rel=\"nofollow sponsored\">How to Change Your Mind</a>, also stresses that the psychological context determines whether the psychedelic experience becomes a source of insight or confusion. For microdosing, this means that a dose without intention risks being an inert chemical encounter, rather than a meaningful engagement.</p>\n\n<p>Lastly, the role of intention is not just psychological but also neurological. Brain imaging studies, like those from Carhart-Harris’ team, show that psychedelics alter the brain's connectivity patterns, but the content of those altered states is shaped by what the mind is set to explore. It’s a dance between chemistry and consciousness, where intention leads.</p>\n\n<h3>4. Making intention work for you: Practical steps</h3>\n\n<p>Setting a meaningful intention for microdosing is more than a casual thought. It requires deliberate preparation, reflection, and follow-through. From my experience and conversations with people who’ve integrated microdosing into their routines, here’s a practical roadmap you can try.</p>\n\n<p><strong>Step 1: Reflect deeply on your 'why'</strong>. Before you dose, spend 10 or 15 minutes journaling or meditating on why you want to microdose. Is it to boost creativity? Reduce anxiety? Improve social connection? Be specific. General wishes like \"feel better\" tend to lead to vague results. You can even write your intention on paper or say it aloud. This simple act makes intention real and tangible.</p>\n\n<p><strong>Step 2: Choose your dose with precision</strong>. Consistency is key in microdosing. A scale like the <a href=\"https://www.amazon.com/dp/B078SZX3ML?tag=spankyspinola-20\" target=\"_blank\" rel=\"nofollow sponsored\">Milligram Scale 0.001g Precision</a> helps you measure exactly. Variability in dose can confound your experience and make intentions harder to track. Start low - around 0.1g of dried mushrooms is common - and adjust slowly.</p>\n\n<p><strong>Step 3: Set a ritual around your dosing</strong>. This can be as simple as sitting quietly with your intention before taking your dose, doing some breathwork, or lighting a candle. This signals to your brain that this moment is different, focused. Rituals prime your psyche to engage intentionally.</p>\n\n<p><strong>Step 4: Stay mindful during the day</strong>. Don’t just dose and forget. Throughout the day, check in with your intention. Are you noticing subtle shifts? Are you more patient, creative, or calm? This ongoing awareness strengthens the mental pathways connected to your goals.</p>\n\n<p><strong>Step 5: Journal your observations</strong>. Write down how you feel each day, what thoughts or emotions arise, and whether you notice patterns linked to your intention. Tracking helps confirm whether your intention is taking root or if it needs recalibration.</p>\n\n<p><strong>Step 6: Be patient and flexible</strong>. Intentions may evolve as you learn more about yourself and the medicine. Maybe your initial intention was to improve focus, but you discover a deeper emotional healing is unfolding. Be open to letting your intention grow and shift.</p>\n\n<p>Lastly, if you’re serious about integrating mind and body health, I recommend reading <a href=\"https://www.amazon.com/dp/0525510311?tag=spankyspinola-20\" target=\"_blank\" rel=\"nofollow sponsored\">The Body Keeps the Score by Bessel van der Kolk</a>. This book helps you understand how trauma and emotional patterns are stored in the body, which intention can gently address with the added help of psychedelics.</p>\n\n<p>Creating intention isn’t about forcing results but about aligning your inner compass with the subtle shifts microdosing offers. This turns a chemical process into a conscious partnership with yourself.</p>\n\n<h3>5. Common challenges: What gets in the way of intention</h3>\n\n<p>Intention-setting sounds simple on paper, but it’s easy to stumble. One common issue is approaching microdosing with impatience or unrealistic expectations. If you expect immediate miracles or dramatic changes, you might feel disappointed, which clouds your intention. Microdosing is subtle; change happens in increments, often invisible until you reflect. I’ve seen this trap trip up even seasoned microdosers.</p>\n\n<p>Another challenge is mental distraction. In our busy lives, it’s hard to slow down and focus on intention fully. Sometimes, people dose while stressed or distracted, which leads to muddled or underwhelming effects. Intention needs clear space to breathe, like a seed needing fertile soil.</p>\n\n<p>There’s also the problem of vague or confusing intentions. Saying “I want to feel better” is too broad. Without clarity, your brain has no specific target, and the subtle shifts of microdosing may scatter rather than gather meaning.</p>\n\n<p>Then there’s the risk of skipping integration altogether. Some folks just microdose daily without reflecting or adjusting. Without integration, intention fades into a background whisper lost in routine. That can turn microdosing into a mechanical habit rather than a mindful practice.</p>\n\n<p>So how do you work through these? First, be honest with yourself. If impatience is creeping in, take a step back. Set a realistic timeline - microdosing is more about steady growth than overnight transformation.</p>\n\n<p>Next, carve out dedicated time for intention-setting, free from distractions. I often recommend mornings, before the day’s chaos, or evenings when you can journal quietly. Even five focused minutes make a difference.</p>\n\n<p>If your intention feels fuzzy, try refining it by asking yourself: What specific feeling or behavior do I want to cultivate? What old patterns do I want to release? Getting granular helps anchor your intention.</p>\n\n<p>Finally, build integration rituals. This might be journaling your experiences, talking with a trusted friend, or gentle movement like yoga. Integration turns the raw material of intention and microdosing into meaningful change.</p>\n\n<p>Remember, intention is a muscle. Sometimes it wobbles, sometimes it shines. The key is to keep practicing, not getting discouraged by the bumps.</p>\n\n<h3>6. Intention in everyday life: The long play</h3>\n\n<p>Microdosing is not a magic pill, it’s a tool - a subtle influence that nudges your brain and mindset. Without intention, it’s like waving a paintbrush without a plan. But with intention, those small nudges accumulate over time, creating shifts in your habits, relationships, and overall mental health.</p>\n\n<p>Think of intention as a seed you plant each time you dose. It needs watering - through daily mindfulness, reflection, and alignment with your goals. Over weeks and months, you might notice that you approach problems with more creativity, handle stress with a calmer mind, or connect with others more authentically. These are not sudden revelations but gentle tendencies emerging.</p>\n\n<p>This long-term perspective is crucial. Even researchers caution that microdosing effects can be subtle and that sustained practice combined with intentional living is what yields noticeable benefits. Integrating your intention into daily life means more than setting it on dosing days - it means carrying it into your work, your relationships, even your self-talk.</p>\n\n<p>In my own journey, I found that intention-setting transformed microdosing from a curious experiment into a form of ongoing self-inquiry. It became a way to check in with my inner compass regularly, gently course-correcting as life shifted. I started noticing patterns: how certain intentions blossomed during creative projects, while others helped me untangle anxious loops.</p>\n\n<p>This is why many seasoned microdosers recommend keeping an intention journal or regular check-ins. Over time, this creates a feedback loop where your intentions adapt and deepen, and microdosing supports that dynamic process.</p>\n\n<p>In a way, intention becomes a bridge between the subtle chemistry of the mushroom and the complex messiness of real life. It’s the thread that weaves the two together, making the microdose not just a moment but a movement toward greater awareness and well-being.</p>\n\n<h3>7. Closing reflection: A quiet invitation to presence</h3>\n\n<p>As you consider the role of intention in microdosing, I invite you to sit with a question: What does it mean to truly show up for yourself in this practice? Intention is not a fixed destination or a box to check. It’s a living, breathing invitation to meet yourself where you are, with honesty and curiosity.</p>\n\n<p>Microdosing offers a subtle shift in perception. But it is your mind - your intention - that decides what that shift reveals. Without intention, you might pass through a room filled with light without noticing the colors on the walls. With intention, you slow down, adjust your gaze, and discover details that inspire new insights and healing.</p>\n\n<p>In many ways, the practice of intention aligns microdosing with a larger spiritual and psychological tradition: the art of mindful presence. It echoes the wisdom of shamans and mystics who know that the medicine is not just in the plant but in the relationship between plant and person.</p>\n\n<p>So, rather than chasing immediate results or forcing change, try to approach your microdosing experience as a conversation with yourself. Set your intention thoughtfully, but leave space for the unexpected. Notice the tiny openings the medicine creates, and be ready to follow them gently wherever they lead.</p>\n\n<p>That’s where the real power lies - not in the dose, not in the chemical alone, but in the quiet mind that meets the medicine with open eyes and a willing heart. As you explore this path, may intention be your companion, your guide, and your reminder that every step, no matter how small, is meaningful.</p>",
  "excerpt": "To approach microdosing as a mere biochemical input is to miss the profound interplay between substance and mind. Intention acts as a silent architect, transforming a subtle nudge into a catalyst for conscious evolution, guiding our awareness toward specific qualities of being.",
  "pullQuote": "Intention is less about dictating the outcome and more about creating a fertile ground for certain possibilities to emerge, a kind of pre-paving of the experiential path.",
  "heroPrompt": "A serene, sun-drenched room with a person sitting in mindful contemplation, a subtle, ethereal glow emanating around them, symbolizing inner peace and clarity. Soft, warm light streams through a window, illuminating dust motes dancing in the air. The atmosphere is one of gentle awakening and thoughtful introspection, with a slight, almost imperceptible shimmer of energy in the air, hinting at subtle shifts in consciousness. NO text, NO drugs visible.",
  "heroAlt": "A person sitting peacefully in a sunlit room, surrounded by a soft, ethereal glow, meditating with a sense of calm and clarity.",
  "heroImage": "https://quiet-medicine.b-cdn.net/images/role-intention-microdosing.webp",
  "ogImage": "https://quiet-medicine.b-cdn.net/og/role-intention-microdosing.webp",
  "faqs": [
    {
      "question": "How does intention differ from expectation in microdosing?",
      "answer": "Intention acts as a compass, guiding your general direction and opening up possibilities for discovery, while expectation is a rigid demand for a specific outcome. An intention allows for flexibility and emergent experiences, whereas an expectation can create resistance and hinder natural flow."
    },
    {
      "question": "Can I microdose effectively without setting an intention?",
      "answer": "While microdosing can still offer benefits without a clear intention, its effects may be unfocused or amplify existing patterns without deliberate direction. Setting an intention channels the subtle energetic shifts, allowing for more targeted growth and deeper integration of insights into daily life."
    }
  ],
  "readingTime": "10 min read",
  "backlinkType": "internal",
  "status": "published",
  "publishDate": "2025-05-21",
  "linkType": "external",
  "wordCount": 2557,
  "queued_at": "2026-03-15T10:00:00.000Z",
  "published_at": "2025-05-21T07:46:00.000Z"
}