{
  "slug": "the-science-of-microdosing-and-neurogenesis-in-the-adult-brain",
  "title": "The Science of Microdosing and Neurogenesis in the Adult Brain",
  "categorySlug": "the-microdose",
  "categoryName": "The Microdose",
  "dateISO": "2026-04-29T17:02:05.682Z",
  "body": "<h2>The Science of Microdosing and Neurogenesis in the Adult Brain</h2>\n\n<p>You might\u2019ve heard people talking about microdosing psychedelics for creativity, mood, or focus. But what if I told you there\u2019s a growing body of science suggesting microdosing could actually promote neurogenesis - the birth of new brain cells - in adults? Yep. Your brain isn\u2019t fixed. It\u2019s still growing, adapting, and healing. And microdosing might be part of that story.</p>\n\n<p>Look, the idea of growing new neurons in an adult brain used to be dismissed as a myth. Scientists once believed we were stuck with the brain cells we were born with. But since the late 1990s, research has flipped that on its head. Adult neurogenesis is real, especially in the hippocampus, the area tied to memory, learning, and emotional regulation.</p>\n\n<p>Now, you might be wondering, \u201cWhat does microdosing have to do with it?\u201d Good question. Let\u2019s break it down, shall we?</p>\n\n<h3>Microdosing 101: What Are We Talking About?</h3>\n\n<p>Microdosing means taking tiny doses of psychedelics, often about one-tenth to one-twentieth of a typical recreational dose. You\u2019re not tripping. You\u2019re barely feeling anything. Yet many report subtle boosts in mood, clarity, and creativity. The substances commonly microdosed include LSD and psilocybin mushrooms.</p>\n\n<p>Here\u2019s the thing, these compounds interact with serotonin receptors in your brain, especially the 5-HT2A receptor. That interaction triggers a cascade of effects, influencing brain plasticity - the ability to change and adapt. Plasticity is where neurogenesis can kick in.</p>\n\n<h3>Science Says: Psychedelics and New Neurons</h3>\n\n<p>Several animal studies show psychedelics encouraging neurogenesis. A 2018 study published in <a href=\"https://www.nature.com/articles/s41598-018-31144-0\" target=\"_blank\" rel=\"nofollow\">Scientific Reports</a> found that psilocybin increased dendritic spine growth in the mouse brain. Dendritic spines are crucial for forming new connections between neurons. More spines mean more opportunities for brain cells to communicate.</p>\n\n<p>Another fascinating piece comes from a 2017 study led by Dr. David Olson at the University of California, Davis. They found that psychedelics like LSD and psilocybin promoted the growth of new neurons and synapses in vitro - meaning in lab-grown brain cells. They called it \u201cneuroplasticity on steroids.\u201d No kidding.</p>\n\n<p>But here\u2019s where it gets interesting for you. While these studies mostly involve large doses, microdosing might encourage milder, yet sustained, neuroplastic changes. That means your brain could be nudged to grow and adapt without the intense effects of a full psychedelic journey.</p>\n\n<h3>How Does Neurogenesis Actually Matter to You?</h3>\n\n<p>Neurogenesis isn\u2019t just a cool scientific term. It\u2019s tied to how you think, feel, and even heal from trauma or depression. The hippocampus, where most adult neurogenesis happens, helps regulate memory and mood. Decreased neurogenesis is linked to depression and anxiety.</p>\n\n<p>So, by encouraging neurogenesis, microdosing might help improve mood, reduce anxiety, and support cognitive function. It\u2019s not magic. It\u2019s brain biology. You\u2019re giving your brain a gentle push to grow new connections and repair old ones.</p>\n\n<p>Honestly, that\u2019s why many people are so drawn to microdosing. It\u2019s a way to support mental wellness without heavy medications or harsh side effects.</p>\n\n<h3>A Closer Look: What Happens in the Brain?</h3>\n\n<p>Okay, so what\u2019s going on inside your skull? Psychedelics act mainly on the 5-HT2A serotonin receptor. When activated, this receptor influences the expression of brain-derived neurotrophic factor (BDNF). Think of BDNF as fertilizer for your brain. It encourages neurons to grow, survive, and connect.</p>\n\n<p>Higher BDNF levels have been linked to improved learning, memory, and mood regulation. They\u2019re even protective against neurodegenerative diseases like Alzheimer\u2019s.</p>\n\n<p>One study in <em>Scientific American</em> explains that psychedelics increase BDNF expression, which then promotes neurogenesis and synaptogenesis (the formation of synapses between neurons). These changes enhance your brain\u2019s plasticity, making it more flexible and adaptable to new experiences.</p>\n\n<p>Does that land? Your brain becomes more like a youthful, bendy sapling instead of a stiff, brittle old tree.</p>\n\n<h3>Microdosing vs. Full Dose: Why Tiny Might Be Better for Growth</h3>\n\n<p>Full psychedelic trips can be powerful. They shake up your brain networks in a big way. But they\u2019re not always practical or comfortable. Microdosing offers a gentler approach. You give your brain just enough stimulus to encourage plasticity and neurogenesis without overwhelming it.</p>\n\n<p>Still, research on microdosing is young. Most data come from anecdotal reports or small studies. But the trends are promising. People report better focus, mood, and emotional resilience after weeks or months of microdosing schedules.</p>\n\n<p>If you want to explore more about how to microdose safely and effectively, I wrote a detailed guide right here: <a href=\"/articles/microdosing-guide\">The Beginner\u2019s Guide to Microdosing</a>. It\u2019s practical, grounded, and written with your well-being in mind.</p>\n\n<h3>Other Ways to Support Neurogenesis Alongside Microdosing</h3>\n\n<p>Here\u2019s a truth: microdosing isn\u2019t a magic bullet. It\u2019s part of a bigger picture. Neurogenesis also responds to lifestyle factors. Here\u2019s what science tells us you can do to boost brain cell growth:</p>\n\n<ul>\n <li><strong>Exercise</strong>: Aerobic exercise, like running or swimming, increases BDNF and promotes hippocampal neurogenesis.</li>\n <li><strong>Sleep</strong>: Quality sleep is essential for brain repair and new neuron formation.</li>\n <li><strong>Nutrition</strong>: Omega-3 fatty acids, antioxidants, and some vitamins support brain health.</li>\n <li><strong>Meditation</strong>: Mindfulness practices have been shown to increase gray matter density, including the hippocampus.</li>\n</ul>\n\n<p>If you\u2019re looking for tools to stay grounded and enhance your mindfulness practice, consider <a href=\"https://www.amazon.com/dp/B073429DV2?tag=spankyspinola-20\" target=\"_blank\" rel=\"nofollow sponsored\">a weighted blanket for grounding (paid link)</a>. It\u2019s helped me personally stay calm and centered, especially on days when the brain feels scattered.</p>\n\n<h3>Why You Should Care: The Real-Life Impact</h3>\n\n<p>Imagine waking up feeling clearer, less anxious, and more engaged with life. That\u2019s what many microdosers describe after weeks or months of consistent practice. They\u2019re not chasing hallucinations or mystical insights. They\u2019re chasing better brain health, emotional balance, and sharper cognition.</p>\n\n<p>Consider the story of Anna, a writer friend of mine. She started microdosing psilocybin mushrooms after struggling with writer\u2019s block and anxiety for years. After a few months, she told me, \u201cI feel like my brain\u2019s firing on all cylinders again. Ideas flow, and my mood\u2019s steadier. It\u2019s like my brain rewired itself.\u201d</p>\n\n<p>Stories like hers aren\u2019t rare. They\u2019re part of a quietly growing wave of people exploring the healing potential of psychedelics without the full trip. It\u2019s accessible, gentle, and promising.</p>\n\n<h3>How to Approach Microdosing Responsibly</h3>\n\n<p>Here\u2019s the bottom line: microdosing isn\u2019t for everyone. You have to be mindful. Start slow. Track your response. And always respect the substance and your body.</p>\n\n<p>If you\u2019re curious about the science and want to expand your understanding of consciousness and the mind, I highly recommend <a href=\"https://www.amazon.com/dp/1451636024?tag=spankyspinola-20\" target=\"_blank\" rel=\"nofollow sponsored\">Waking Up by Sam Harris (paid link)</a>. It\u2019s a clear, thoughtful exploration of meditation, consciousness, and the mind\u2019s mysteries. No fluff.</p>\n\n<p>Also, remember to check the legal status of psychedelics where you live. And if you have personal or family history of psychosis, talk to a healthcare professional before experimenting. Safety first.</p>\n\n<h3>The Future of Psychedelic Science and Brain Health</h3>\n\n<p>The science is moving fast. Clinical trials are underway exploring psilocybin for depression, PTSD, and addiction. Researchers are keenly interested in how psychedelics affect brain plasticity and neurogenesis because those processes underlie healing and recovery.</p>\n\n<p>Truth is, your brain\u2019s ability to grow and change is one of the most exciting frontiers in neuroscience. Microdosing could be a tool to gently nudge that process forward. But it\u2019s only one part of the story.</p>\n\n<p>If you want to explore how consciousness and healing connect on a broader level, swing by my site at <a href=\"https://kalesh.love\" target=\"_blank\" rel=\"nofollow\">kalesh.love</a>. You\u2019ll find insights, guides, and a community that respects your journey.</p>\n\n<h3>Bonus: Small Tools That Support Your Brain and Body</h3>\n\n<p>To round things out, here\u2019s something practical I use almost daily: <a href=\"https://www.amazon.com/dp/B08FR8MPCW?tag=spankyspinola-20\" target=\"_blank\" rel=\"nofollow sponsored\">an acupressure mat and pillow set (paid link)</a>. It\u2019s great for releasing tension, improving circulation, and calming the nervous system. When you\u2019re supporting neurogenesis, every bit of stress relief counts.</p>\n\n<p>And if you want a compelling read about the living world\u2019s unseen connections, check out <a href=\"https://www.amazon.com/dp/0525510311?tag=spankyspinola-20\" target=\"_blank\" rel=\"nofollow sponsored\">Entangled Life by Merlin Sheldrake (paid link)</a>. It\u2019s a mind-opening look at fungi and their role in ecosystems. Plus, fungi are connected to psilocybin. Know what I mean?</p>\n\n<h3>Wrapping It Up: What You Can Take Away</h3>\n\n<p>Microdosing isn\u2019t just about feeling better for a few hours. It\u2019s about supporting your brain\u2019s natural ability to grow and heal. The science on neurogenesis is real, tangible, and backed by serious research. Psychedelic compounds, even at low doses, influence the receptors and growth factors that help your brain rewire and regenerate.</p>\n\n<p>Does that spark your curiosity? Great! Just move forward with care, respect, and plenty of research.</p>\n\n<p>If you want more on this, or to learn about other ways consciousness and wellness connect, keep exploring my articles here on <a href=\"/articles/the-microdose\">The Microdose</a>. We\u2019re in this together.</p>\n\n<div class=\"disclaimer-card\">\n <p><strong>Disclaimer:</strong> This content is for educational purposes only and does not constitute medical advice. Always consult a qualified healthcare provider before making changes to your health regimen.</p>\n</div>",
  "excerpt": "The Science of Microdosing and Neurogenesis in the Adult Brain \n\n You might\u2019ve heard people talking about microdosing psychedelics for creativity, mood, or focus. But what if I told you there\u2019s a gro...",
  "heroImage": "https://quiet-medicine.b-cdn.net/library/lib-31.webp",
  "ogImage": "https://quiet-medicine.b-cdn.net/library/lib-31.webp",
  "heroAlt": "Illustration for The Science of Microdosing and Neurogenesis in the Adult Brain",
  "readingTime": 5,
  "status": "published",
  "queued_at": "2026-04-29T17:02:05.682Z",
  "published_at": "2025-09-29T08:00:00.000Z",
  "publishDate": "2025-09-29",
  "wordCount": 1455
}