{
  "slug": "understanding-the-training-requirements-for-psychedelic-therapists",
  "title": "Understanding the Training Requirements for Psychedelic Therapists",
  "categorySlug": "the-clinic",
  "categoryName": "The Clinic",
  "dateISO": "2026-04-29T17:02:05.697Z",
  "body": "<h2>Understanding the Training Requirements for Psychedelic Therapists</h2>\n\n<h3>1. Opening Hook: A Moment in the Psychedelic Space</h3>\n<p>Years ago, I found myself sitting quietly beside a friend who was about to begin on a psilocybin journey. The room was hushed, thick with anticipation, the scent of sage curling in the air. It wasn’t just about the mushroom itself but the subtle, almost sacred role I had as a guide, a companion through something deeply personal and vulnerable. That moment made me realize how essential it is for anyone stepping into the role of a psychedelic therapist to be more than just well-versed in theory. They must embody presence, empathy, and rigorous training to support that journey safely.</p>\n\n<p>How do you prepare for such a responsibility? What kind of training equips someone to hold space for experiences that often break down the very fabric of one’s reality? The idea of psychedelic therapy has moved beyond the fringe and into the spotlight, garnering immense interest, yet the path to becoming a competent, ethical therapist is anything but straightforward.</p>\n\n<p>When I first started in this field, there were few formal programs or clear guidelines. Today, with the rising wave of research and legalization efforts, many institutions have started offering training courses, certifications, and immersive experiences. But not every program is created equal. And for those drawn to this work, understanding the full scope of what it takes to be a psychedelic therapist isn’t just about checking boxes on a credential list; it’s about cultivating a deep understanding of the medicine, the psyche, and the human condition itself.</p>\n\n<p>Reflecting on my early days, I realize how much I learned the hard way - through direct experiences, mistakes, and long conversations with mentors who were often as much explorers as practitioners. This article lays out what I’ve gathered over the years about the training requirements for psychedelic therapists, weaving together neuroscience, research, practical advice, and reflections on the challenges you’ll face. If you’re considering this path, buckle up - there’s a lot to unpack.</p>\n\n<h3>2. Core Concept Explanation: What Does Psychedelic Therapy Training Entail?</h3>\n<p>At its core, psychedelic therapy training is about preparing someone to safely and skillfully guide others through altered states of consciousness induced by substances like psilocybin, MDMA, or ketamine. Unlike traditional talk therapy, psychedelic-assisted therapy involves periods of non-ordinary experience, sometimes deeply challenging or mystical. This means therapists need specific skills beyond standard clinical training.</p>\n\n<p>First, there’s the biomedical understanding of how these substances affect brain function. Research by Robin Carhart-Harris and his team at Imperial College London has shown how psychedelics disrupt the default mode network (DMN), the brain network associated with self-referential thoughts and ego boundaries. Training includes grounding therapists in this neuroscience foundation, so they grasp why these medicines can temporarily dissolve rigid thought patterns, allowing people to access emotional breakthroughs or new perspectives.</p>\n\n<p>Then comes the psychological training. Drawing from the work of pioneers like Stanislav Grof, who first explored psychedelic states in a therapeutic context, therapists learn to recognize common patterns in psychedelic experiences - such as facing inner traumas, encountering archetypal visions, or navigating existential insights. This requires skills in trauma-informed care, emotional regulation, and crisis intervention, because not every session is a smooth ride.</p>\n\n<p>Importantly, training also emphasizes the ethical and legal field. Psychedelic substances remain federally illegal in most places, so therapists must understand how to work within local regulations and the evolving policies around these therapies. Programs often combine academic knowledge with supervised hands-on practice, ensuring that therapists build competence through real-world experience, under mentorship.</p>\n\n<p>The therapist’s role isn’t to “fix” or “direct” but to hold space, support integration, and help clients make meaning of their experiences. This demands a high level of self-awareness and personal work. Many training programs require candidates to have undergone their own psychedelic experiences or therapy to better empathize with clients. This isn’t a luxury; it’s essential.</p>\n\n<h3>3. Research and Evidence: Studies Defining the Therapist’s Role</h3>\n<p>Scientific research on psychedelic therapy provides valuable guidelines about what effective therapist training should include. Dr. Matthew Johnson’s work at Johns Hopkins University has been key. In his psilocybin studies for depression, Johnson’s team found that the quality and safety of the therapeutic setting, including the skill of the guide, significantly impacted outcomes. The therapist wasn’t just an observer but an active participant ensuring safety and emotional support.</p>\n\n<p>Griffiths et al. (2016) demonstrated in their landmark study that psilocybin sessions combined with psychological support produced substantial, lasting reductions in depression and anxiety. Their protocol included preparatory sessions, the dosing session with attentive monitors, and multiple integration meetings post-experience. This model highlights the continuum of care necessary, which therapists must master during training.</p>\n\n<p>Another key contribution comes from MAPS (Multidisciplinary Association for Psychedelic Studies), especially in the development of MDMA-assisted therapy for PTSD. Researchers like Michael Mithoefer have shown that therapists require specialized training to move through trauma-related material that often surfaces during sessions. They undergo multi-level certification processes, including didactic learning, role-playing, and supervised practice.</p>\n\n<p>The importance of trauma-informed care is echoed in Bessel van der Kolk’s work, especially in his book <a href=\"https://www.amazon.com/dp/0525510311?tag=spankyspinola-20\" target=\"_blank\" rel=\"nofollow sponsored\">The Body Keeps the Score</a>. Therapists trained in psychedelic-assisted treatment must understand how trauma is stored in the body, as psychedelics often bring somatic memories to the surface. Without this foundational knowledge, therapists risk retraumatizing clients.</p>\n\n<p>Research also underscores the therapist’s role in integration, the process of making sense of psychedelic experiences after the fact. Clinical trials often include integration sessions where therapists guide clients in processing insights, developing new coping strategies, and grounding changes into daily life. This long-term work demands both clinical skill and patience, which training programs reflect.</p>\n\n<h3>4. Practical Application: What Training Looks Like for You</h3>\n<p>If you’re drawn to becoming a psychedelic therapist, what steps can you take right now? First, having a solid foundation in mental health or counseling is often required. Many training programs stipulate that candidates hold degrees or licenses in psychology, social work, nursing, or related fields. If you’re starting without this background, look into programs that offer preparatory courses or foundational education first.</p>\n\n<p>Next, seek out reputable training programs. Organizations like the California Institute of Integral Studies (CIIS), Fluence, and the Psychedelic Society offer training that blends theory, practice, and supervised experience. These courses often stretch over months, including live sessions, role-playing exercises, and mentorship.</p>\n\n<p>Personal psychedelic experience can be controversial but is frequently encouraged or required. Going through a psychedelic journey yourself, in a safe and legal environment, helps develop empathy and insight. This isn’t about recreational use but deeply understanding the medicine from the inside. I always recommend journaling your experiences extensively; a <a href=\"https://www.amazon.com/dp/B09VK9S4JB?tag=spankyspinola-20\" target=\"_blank\" rel=\"nofollow sponsored\">Journaling Notebook Leather Bound</a> is perfect for capturing these subtle shifts and reflections.</p>\n\n<p>Alongside formal training, immerse yourself in the literature. Michael Pollan’s <a href=\"https://www.amazon.com/dp/1594774021?tag=spankyspinola-20\" target=\"_blank\" rel=\"nofollow sponsored\">How to Change Your Mind</a> is a must-read, offering a narrative-rich understanding of the medicine and its history. Meanwhile, Grady and his research team’s work sheds light on the neurobiology you need to grasp.</p>\n\n<p>Finally, seek mentorship whenever possible. Psychedelic therapy is still an emerging field, and hands-on guidance can make all the difference. Many established therapists offer apprentice-style learning or community groups where you can practice skills in a safe setting. Never underestimate the value of honest feedback and peer support.</p>\n\n<h3>5. Common Challenges and How to Work Through Them</h3>\n<p>Stepping into psychedelic therapy training is rewarding, but it brings a handful of obstacles. One common challenge is navigating your own biases and emotional wounds. As therapists, we’re not blank slates. Psychedelic experiences can amplify unresolved issues, sometimes leading to countertransference or emotional overwhelm during sessions. Training programs increasingly focus on self-work, encouraging candidates to engage in their own therapy or spiritual practices to build resilience.</p>\n\n<p>Another difficulty is the legal gray area. Because many psychedelics are federally illegal, training programs and practitioners must balance adhering to the law with providing ethical, evidence-based care. This means many therapists start with ketamine-assisted therapy, which is legal and FDA-approved, before moving to substances like psilocybin where regulations are loosening. Being patient and informed about the evolving legal situation helps manage frustration.</p>\n\n<p>There’s also the challenge of managing client expectations. Psychedelic therapy is not magic. Sometimes clients expect instantaneous healing, but the medicine often opens a door rather than solves problems outright. Training emphasizes clear communication, setting realistic goals, and helping clients understand the integration process’s importance.</p>\n\n<p>Burnout is real in this field. The emotional intensity, coupled with the responsibility, can wear on therapists. Building a support network, regular supervision, and self-care routines are non-negotiable. Programs that include peer groups and reflective practice help therapists maintain balance.</p>\n\n<p>Lastly, some therapists struggle with the balance between being present and maintaining professional boundaries during sessions. Psychedelic states can feel intimate or spiritual, but therapists must keep ethical standards front and center. Training scenarios, role plays, and ethical discussions prepare therapists to hold space without overstepping.</p>\n\n<h3>6. Integration with Daily Life: A Therapist’s Long-Term Perspective</h3>\n<p>Training doesn’t stop when your certificate arrives. Being a psychedelic therapist means committing to ongoing learning and integration - not just for clients but for yourself. Psychedelic therapy is an evolving field, and staying current with research, laws, and community best practices is a lifelong process.</p>\n\n<p>On a personal level, integrating what you learn from your clients’ journeys can profoundly affect your worldview and emotional field. This work pulls therapists into deeper questions about consciousness, identity, and healing. I’ve found that maintaining my own practice - whether meditation, journaling, or somatic work - helps me stay grounded and open.</p>\n\n<p>Effective therapists help clients bring psychedelic insights into their daily lives, fostering sustained change. This often involves coaching around lifestyle, relationships, and mental health strategies. Therapists trained in integration methods support clients in translating mystical or emotional breakthroughs into practical steps like mindfulness, improved boundaries, or creative expression.</p>\n\n<p>Beyond direct client work, many psychedelic therapists engage with their communities, offering workshops, support groups, or advocacy. This broadens the impact and keeps therapists connected to the larger conversation about these medicines’ role in society.</p>\n\n<p>Because psychedelic therapy is so relational, therapists often find their work influencing their own relationships and sense of purpose. Setting boundaries around work hours, ongoing supervision, and peer connection ensures you don’t lose yourself in the process.</p>\n\n<h3>7. Closing Reflection: The Weight and Wonder of the Therapist’s Role</h3>\n<p>Becoming a psychedelic therapist is stepping into a role that blends artistry, science, and deep humanity. It’s a responsibility that carries weight because you are guiding someone through experiences that can rearrange their very sense of self. I’ll never forget the quiet moments after a session, when a client stares out the window, tears slipping down, whispering about seeing their past with new eyes. That raw vulnerability demands that the therapist be more than knowledgeable - they must be steady, compassionate, and endlessly curious.</p>\n\n<p>Thinking about training, I realize it’s less about a checklist and more about a lifelong commitment to understanding human consciousness in its messy, beautiful complexity. It means being willing to look inward just as much as outward, to hold space for others while acknowledging your own limits.</p>\n\n<p>Psychedelic therapy could easily become a tool for quick fixes or spiritual bypassing, but true healing requires patience, humility, and skill. The training paths open today may feel fragmented, but this is part of an emerging culture that still needs time to find its form. For those willing to walk this road, the promise is deep - a chance to participate in healing in ways our society has long ignored.</p>\n\n<p>In the end, the question I come back to is not about what training one must have, but about the kind of therapist one wants to be. Do you want to be a guide who holds steady when the storm hits? Can you sit with not-knowing and offer kindness without judgment? If so, then every hour spent in training is a step toward a deeply meaningful calling that goes far beyond the classroom.</p>",
  "excerpt": "Understanding the Training Requirements for Psychedelic Therapists \n\n So, you’re curious about what it takes to become a psychedelic therapist, huh? Right?! This field is growing fast, and with that...",
  "heroImage": "https://quiet-medicine.b-cdn.net/library/lib-07.webp",
  "ogImage": "https://quiet-medicine.b-cdn.net/library/lib-32.webp",
  "heroAlt": "Illustration for Understanding the Training Requirements for Psychedelic Therapists",
  "readingTime": 6,
  "status": "queued",
  "queued_at": "2026-04-29T17:02:05.697Z",
  "published_at": "2027-06-28T08:00:00.000Z",
  "publishDate": "2027-06-28",
  "wordCount": 1993
}